{
    "United Kingdom": {
        "gdp_rank": 6,
        "spike_score": 1856.0,
        "trends": [
            {
                "record_id": "1310566998",
                "url": "https://www.rhyljournal.co.uk/news/national/26224346.keir-starmer-bats-away-criticism-front-backbenchers-pmqs-bout/",
                "related_urls": [
                    "https://www.salisburyjournal.co.uk/news/national/26224346.keir-starmer-bats-away-criticism-front-backbenchers-pmqs-bout/"
                ],
                "title": "",
                "mentions": 60,
                "sources": 10,
                "goldstein": 7.0,
                "tone": -2.33502538071066,
                "score": 502.0
            },
            {
                "record_id": "1310399683",
                "url": "https://www.dunfermlinepress.com/news/national/26221505.government-announces-urgent-review-anomalous-business-rates-hikes/",
                "related_urls": [],
                "title": "",
                "mentions": 180,
                "sources": 12,
                "goldstein": 3.0,
                "tone": -0.323195157311791,
                "score": 499.0
            },
            {
                "record_id": "1310356023",
                "url": "https://www.halesowennews.co.uk/news/national/26219193.extreme-weather-causes-major-travel-disruption-temperature-near-40c/",
                "related_urls": [
                    "https://www.peeblesshirenews.com/news/national/26219193.extreme-weather-causes-major-travel-disruption-temperature-near-40c/",
                    "https://www.northwalespioneer.co.uk/news/national/26219193.extreme-weather-causes-major-travel-disruption-temperature-near-40c/",
                    "https://www.dailyecho.co.uk/news/national/26219193.extreme-weather-causes-major-travel-disruption-temperature-near-40c/"
                ],
                "title": "",
                "mentions": 120,
                "sources": 12,
                "goldstein": 3.0,
                "tone": -3.10077519379845,
                "score": 363.0
            },
            {
                "record_id": "1310461047",
                "url": "https://www.ludlowadvertiser.co.uk/news/national/26222268.uk-braced-record-breaking-heat-rare-red-weather-warnings-come-force/",
                "related_urls": [
                    "https://www.falmouthpacket.co.uk/news/national/26222268.uk-braced-record-breaking-heat-rare-red-weather-warnings-come-force/"
                ],
                "title": "",
                "mentions": 130,
                "sources": 13,
                "goldstein": 7.0,
                "tone": 0.105253925094286,
                "score": 273.0,
                "keyword": "영국 폭염 경보",
                "hook": "영국 전역에 기록적인 폭염이 덮치며 사상 첫 적색 경보가 발령되었습니다.",
                "script": "지금 영국이 불타고 있습니다. 기온이 40도에 육박하는 유례없는 폭염으로 적색 경보가 내려졌습니다. 외출 시 각별히 주의하십시오. 기록적인 더위, 지금 바로 확인하세요.",
                "sentiment": "warning"
            },
            {
                "record_id": "1310388593",
                "url": "https://www.bicesteradvertiser.net/news/national/26220593.scottish-ministers-will-not-appeal-court-ruling-trans-prisoners-swinney-says/",
                "related_urls": [],
                "title": "",
                "mentions": 120,
                "sources": 6,
                "goldstein": 1.0,
                "tone": -4.90367775831874,
                "score": 219.0
            }
        ],
        "last_updated": "2026-06-25 07:39:03 KST",
        "current_rank": 1
    },
    "United States": {
        "gdp_rank": 1,
        "spike_score": 1562.0,
        "trends": [
            {
                "record_id": "1310460991",
                "url": "https://1190talkradio.iheart.com/content/2026-06-23-new-york-school-board-vice-president-arrested-on-child-pornography-charges/",
                "related_urls": [
                    "https://55krc.iheart.com/content/2026-06-23-new-york-school-board-vice-president-arrested-on-child-pornography-charges/"
                ],
                "title": "",
                "mentions": 100,
                "sources": 1,
                "goldstein": -7.0,
                "tone": -6.9410624249334,
                "score": 427.0,
                "keyword": "뉴욕 교육위원 체포",
                "hook": "뉴욕 교육위원회 부위원장이 아동 포르노 혐의로 긴급 체포되었습니다.",
                "script": "충격적인 소식입니다. 뉴욕 교육위원회 부위원장이 아동 포르노 소지 혐의로 경찰에 붙잡혔습니다. 교육 현장의 수장이 저지른 범죄에 지역 사회가 큰 충격에 빠졌습니다. 자세한 수사 내용은 지금 즉시 확인하십시오.",
                "sentiment": "warning"
            },
            {
                "record_id": "1310437279",
                "url": "https://www.halesowennews.co.uk/news/national/26222191.trump-blames-vandals-damage-reflecting-pool/",
                "related_urls": [],
                "title": "",
                "mentions": 140,
                "sources": 14,
                "goldstein": -10.0,
                "tone": -3.47826086956523,
                "score": 425.0
            },
            {
                "record_id": "1310577090",
                "url": "https://wbhpam.iheart.com/content/2026-06-24-search-continues-for-giraffe-that-escaped-from-texas-ranch-last-week/",
                "related_urls": [],
                "title": "",
                "mentions": 170,
                "sources": 1,
                "goldstein": -2.0,
                "tone": -0.831024930747919,
                "score": 311.5
            },
            {
                "record_id": "1310282032",
                "url": "https://www.mendocinobeacon.com/2026/06/22/trump-ufc-fbi-arrests/",
                "related_urls": [],
                "title": "",
                "mentions": 50,
                "sources": 5,
                "goldstein": -10.0,
                "tone": -7.58226037195993,
                "score": 209.0
            },
            {
                "record_id": "1310479197",
                "url": "https://www.yahoo.com/news/politics/articles/federal-judge-blocks-ice-making-015822093.html",
                "related_urls": [],
                "title": "",
                "mentions": 310,
                "sources": 1,
                "goldstein": -6.5,
                "tone": -12.8371628371628,
                "score": 189.5
            }
        ],
        "last_updated": "2026-06-25 07:39:03 KST",
        "current_rank": 2
    },
    "South Korea": {
        "gdp_rank": 14,
        "spike_score": 1141.0,
        "trends": [
            {
                "record_id": "1310470455",
                "url": "https://www.newspim.com/news/view/20260624000147",
                "related_urls": [
                    "https://www.newspim.com/news/view/20260623000084"
                ],
                "title": "",
                "mentions": 400,
                "sources": 1,
                "goldstein": 5.0,
                "tone": -10.2470462362257,
                "score": 1141.0
            }
        ],
        "last_updated": "2026-06-25 07:39:03 KST",
        "current_rank": 3
    },
    "Australia": {
        "gdp_rank": 13,
        "spike_score": 981.0,
        "trends": [
            {
                "record_id": "1310518990",
                "url": "https://www.bendigoadvertiser.com.au/story/9298763/australia-responsible-for-offshore-detainees-un-report/",
                "related_urls": [],
                "title": "",
                "mentions": 120,
                "sources": 6,
                "goldstein": -6.5,
                "tone": -6.23231994418722,
                "score": 268.5
            },
            {
                "record_id": "1310332761",
                "url": "https://www.therural.com.au/story/9297970/health-company-accused-of-using-fake-doctors-for-sales/",
                "related_urls": [],
                "title": "",
                "mentions": 70,
                "sources": 7,
                "goldstein": 4.0,
                "tone": -3.48478330803807,
                "score": 246.0
            },
            {
                "record_id": "1310531072",
                "url": "https://www.theadvocate.com.au/story/9298782/australians-in-iran-iraq-directed-local-jewish-attacks/",
                "related_urls": [],
                "title": "",
                "mentions": 180,
                "sources": 9,
                "goldstein": 3.4,
                "tone": -3.49507323640841,
                "score": 196.5
            },
            {
                "record_id": "1310287574",
                "url": "https://www.examiner.com.au/story/9297304/out-of-context-hanson-defends-parental-leave-stance/",
                "related_urls": [],
                "title": "",
                "mentions": 144,
                "sources": 6,
                "goldstein": -5.0,
                "tone": -0.720393760923981,
                "score": 175.0
            },
            {
                "record_id": "1310340945",
                "url": "https://www.bendigoadvertiser.com.au/story/9297176/reports-for-sick-birds-surge-but-no-new-cases-detected/",
                "related_urls": [],
                "title": "",
                "mentions": 100,
                "sources": 5,
                "goldstein": 0.0,
                "tone": -5.23560148718523,
                "score": 95.0
            }
        ],
        "last_updated": "2026-06-25 07:39:03 KST",
        "current_rank": 4
    },
    "China": {
        "gdp_rank": 2,
        "spike_score": 690.5,
        "trends": [
            {
                "record_id": "1310481349",
                "url": "https://en.people.cn/n3/2026/0624/c90000-20470230.html",
                "related_urls": [],
                "title": "",
                "mentions": 140,
                "sources": 1,
                "goldstein": 7.0,
                "tone": 1.53846153846154,
                "score": 398.0
            },
            {
                "record_id": "1310433622",
                "url": "https://g1.globo.com/mg/sul-de-minas/noticia/2026/06/23/trabalhadores-denunciam-agressao-fisica-e-param-fabrica-de-multinacional-chinesa-em-mg.ghtml",
                "related_urls": [
                    "https://g1.globo.com/mg/sul-de-minas/noticia/2026/06/24/producao-e-retomada-em-fabrica-de-multinacional-chinesa-apos-denuncia-de-agressao-fisica-em-mg.ghtml"
                ],
                "title": "",
                "mentions": 90,
                "sources": 1,
                "goldstein": -4.0,
                "tone": -7.88990825688074,
                "score": 223.0,
                "keyword": "중국 공장 폭동",
                "hook": "해외 진출한 중국 기업 공장에서 노동자 폭행 사건이 터지며 공장 가동이 전면 중단되었습니다.",
                "script": "중국 기업의 해외 공장에서 노동자들이 폭행을 당했다는 사실이 폭로됐습니다. 분노한 노동자들이 공장 가동을 멈추고 거세게 항의하고 있습니다. 글로벌 기업의 민낯, 지금 확인하세요.",
                "sentiment": "negative"
            },
            {
                "record_id": "1310311217",
                "url": "https://www.singletonargus.com.au/story/9297665/shocking-toxic-herbicide-approved-for-ongoing-use/",
                "related_urls": [],
                "title": "",
                "mentions": 75,
                "sources": 5,
                "goldstein": -4.4,
                "tone": -4.70395958937339,
                "score": 69.5
            }
        ],
        "last_updated": "2026-06-25 07:39:03 KST",
        "current_rank": 5
    },
    "Germany": {
        "gdp_rank": 3,
        "spike_score": 489.0,
        "trends": [
            {
                "record_id": "1310555425",
                "url": "http://www.come-on.de/politik/merz-ruft-im-bundestag-zu-mitarbeit-an-reformen-auf-zr-94366813.html",
                "related_urls": [],
                "title": "",
                "mentions": 200,
                "sources": 9,
                "goldstein": 3.0,
                "tone": 2.10525735236911,
                "score": 133.0
            },
            {
                "record_id": "1310303977",
                "url": "https://www.muensterschezeitung.de/nachrichten/politik/vorbild-fuer-deutschland-wie-schweden-die-rente-finanziert-3580705",
                "related_urls": [],
                "title": "",
                "mentions": 60,
                "sources": 6,
                "goldstein": -5.0,
                "tone": -0.32476313139752,
                "score": 124.0
            },
            {
                "record_id": "1310555734",
                "url": "http://www.merkur.de/politik/studie-zu-gewalt-an-schulen-erschuettert-bayern-betont-null-toleranz-zr-94366805.html",
                "related_urls": [],
                "title": "",
                "mentions": 70,
                "sources": 6,
                "goldstein": -2.0,
                "tone": -6.46833643380057,
                "score": 109.0,
                "keyword": "바이에른 학교 폭력",
                "hook": "독일 바이에른 주 학교 내 폭력 사태가 임계치를 넘어서며 교육 당국이 비상에 걸렸습니다.",
                "script": "독일 바이에른 주 학교들이 폭력으로 얼룩지고 있습니다. 충격적인 연구 결과가 발표되자 정부는 '무관용 원칙'을 선포했습니다. 우리 아이들이 위험합니다. 지금 바로 알아보세요.",
                "sentiment": "warning"
            },
            {
                "record_id": "1310535133",
                "url": "https://www.noz.de/deutschland-welt/panorama/artikel/social-media-prien-fuer-13-als-gesetzliche-altersgrenze-50825486",
                "related_urls": [],
                "title": "",
                "mentions": 70,
                "sources": 7,
                "goldstein": 3.0,
                "tone": 0.664962226535801,
                "score": 64.0
            },
            {
                "record_id": "1310601914",
                "url": "http://www.fnp.de/welt/das-ist-herzzerreissend-politiker-kaempft-fuer-soli-eis-und-hat-eine-konkrete-idee-zr-94367228.html",
                "related_urls": [],
                "title": "",
                "mentions": 60,
                "sources": 6,
                "goldstein": 3.4,
                "tone": -1.23175310893809,
                "score": 59.0
            }
        ],
        "last_updated": "2026-06-25 07:39:03 KST",
        "current_rank": 6
    },
    "Indonesia": {
        "gdp_rank": 15,
        "spike_score": 280.0,
        "trends": [
            {
                "record_id": "1310309380",
                "url": "https://batam.tribunnews.com/news/686961/belanja-pegawai-apbd-tanggamus-2026-capai-43-persen-di-atas-batas-ideal-pemerintah",
                "related_urls": [],
                "title": "",
                "mentions": 120,
                "sources": 1,
                "goldstein": 3.0,
                "tone": -0.887404613353171,
                "score": 77.0,
                "keyword": "탕가무스 재정 위기",
                "hook": "인도네시아 탕가무스 지역의 공무원 급여 지출이 임계치를 넘어 국가 재정을 위협하고 있습니다.",
                "script": "탕가무스 지방 예산의 43%가 공무원 인건비로 증발했습니다. 정부가 정한 이상적인 한도를 완전히 벗어난 수치입니다. 지역 경제가 붕괴할 위험에 처했습니다. 주민들의 복지 예산은 도대체 어디로 가는 걸까요? 지금 즉시 재정 건전성 확보가 시급합니다.",
                "sentiment": "warning"
            },
            {
                "record_id": "1310515545",
                "url": "https://www.jpnn.com/foto/politik/31443/komisi-ix-dpr-raker-dengan-menteri-kependudukan-dan-pembangunan-keluarga",
                "related_urls": [],
                "title": "",
                "mentions": 110,
                "sources": 1,
                "goldstein": 1.0,
                "tone": -0.929368029739773,
                "score": 62.0
            },
            {
                "record_id": "1310545089",
                "url": "https://www.tempo.co/foto/arsip/menyusuri-trotoar-ala-labirin-di-thamrin-2271372",
                "related_urls": [],
                "title": "",
                "mentions": 60,
                "sources": 1,
                "goldstein": 3.4,
                "tone": 0.0,
                "score": 49.0
            },
            {
                "record_id": "1310482539",
                "url": "https://www.jawapos.com/bisnis/2606240036/ihsg-diprediksi-lanjutkan-pelemahan-pada-24-juni",
                "related_urls": [],
                "title": "",
                "mentions": 60,
                "sources": 1,
                "goldstein": 3.0,
                "tone": 0.47619047619047,
                "score": 47.0
            },
            {
                "record_id": "1310412962",
                "url": "https://www.liputan6.com/islami/read/7894632/doa-memohon-perlindungan-dari-penyakit-berat-dan-wabah-lengkap-arab-latin-dan-artinya",
                "related_urls": [],
                "title": "",
                "mentions": 56,
                "sources": 1,
                "goldstein": 3.0,
                "tone": 5.08982035928142,
                "score": 45.0
            }
        ],
        "last_updated": "2026-06-25 07:39:03 KST",
        "current_rank": 7
    },
    "Russia": {
        "gdp_rank": 11,
        "spike_score": 262.0,
        "trends": [
            {
                "record_id": "1310288257",
                "url": "https://english.news.cn/20260623/1c2126966e1a49598e735380dcbd4597/c.html",
                "related_urls": [],
                "title": "",
                "mentions": 112,
                "sources": 1,
                "goldstein": 0.0,
                "tone": -3.23974082073433,
                "score": 86.0
            },
            {
                "record_id": "1310457902",
                "url": "https://www.kilburntimes.co.uk/news/national/26222271.uk-defence-spending-gap-matter-concern-nato-says-former-chief/",
                "related_urls": [],
                "title": "",
                "mentions": 64,
                "sources": 8,
                "goldstein": -7.0,
                "tone": -0.38461538461538,
                "score": 83.0
            },
            {
                "record_id": "1310419643",
                "url": "https://www.svoboda.org/a/33776142.html",
                "related_urls": [],
                "title": "",
                "mentions": 70,
                "sources": 1,
                "goldstein": -4.0,
                "tone": -0.15527950310559,
                "score": 57.0
            },
            {
                "record_id": "1310332161",
                "url": "https://www.b92.net/automobili/aktuelno/244156/nova-pravila-na-tehnickim-pregledima-u-srbiji-kako-ce-izgledati-kontrola-vozila-i-koliko-kosta-registracija/vest",
                "related_urls": [],
                "title": "",
                "mentions": 68,
                "sources": 1,
                "goldstein": 0.0,
                "tone": -0.639463013395266,
                "score": 36.0
            }
        ],
        "last_updated": "2026-06-25 07:39:03 KST",
        "current_rank": 8
    },
    "France": {
        "gdp_rank": 7,
        "spike_score": 185.0,
        "trends": [
            {
                "record_id": "1310512423",
                "url": "https://www.hna.de/leute/im-privatjet-unterwegs-ex-prinz-andrew-geniesst-offenbar-champagner-und-reiturlaub-in-frankreich-zr-94365957.html",
                "related_urls": [],
                "title": "",
                "mentions": 60,
                "sources": 5,
                "goldstein": -5.0,
                "tone": -0.78328981723237,
                "score": 65.0
            },
            {
                "record_id": "1310494853",
                "url": "https://www.thecarillon.com/local/2026/06/23/springfield-pride-celebrates-third-year-first-pride-walk",
                "related_urls": [],
                "title": "",
                "mentions": 84,
                "sources": 1,
                "goldstein": 3.4,
                "tone": 5.24412296564196,
                "score": 61.0
            },
            {
                "record_id": "1310332678",
                "url": "https://www.cravenherald.co.uk/news/national/26218720.red-heatwave-alert-covers-much-france-20-drowning-deaths-reported/",
                "related_urls": [],
                "title": "",
                "mentions": 70,
                "sources": 7,
                "goldstein": -2.0,
                "tone": -4.54545454545454,
                "score": 59.0,
                "keyword": "프랑스 폭염 참사",
                "hook": "프랑스 전역을 덮친 살인적인 폭염으로 벌써 20명의 사망자가 발생했습니다.",
                "script": "프랑스에 비상이 걸렸습니다. 기록적인 폭염으로 인해 익사 사고를 포함해 20명이 목숨을 잃었습니다. 적색 경보가 내려진 프랑스 현지 상황을 지금 바로 전해드립니다.",
                "sentiment": "warning"
            }
        ],
        "last_updated": "2026-06-25 07:39:03 KST",
        "current_rank": 9
    },
    "Italy": {
        "gdp_rank": 8,
        "spike_score": 116.0,
        "trends": [
            {
                "record_id": "1310368615",
                "url": "https://www.finanzen.net/nachricht/aktien/deutschland-rueckt-global-auf-platz-vier-des-solarausbaus-15759928",
                "related_urls": [],
                "title": "",
                "mentions": 60,
                "sources": 6,
                "goldstein": 3.4,
                "tone": 0.781327589688875,
                "score": 59.0
            },
            {
                "record_id": "1310512359",
                "url": "https://www.kreiszeitung.de/welt/schlimmste-hitzewelle-seit-2003-italien-kollabiert-blackouts-arbeitsverbote-und-notaufnahmen-zr-94365951.html",
                "related_urls": [],
                "title": "",
                "mentions": 70,
                "sources": 6,
                "goldstein": -2.0,
                "tone": -5.74468085106383,
                "score": 57.0
            }
        ],
        "last_updated": "2026-06-25 07:39:03 KST",
        "current_rank": 10
    },
    "India": {
        "gdp_rank": 5,
        "spike_score": 99.0,
        "trends": [
            {
                "record_id": "1310301996",
                "url": "https://www.legallyindia.com/convos/topic/486166-Lex-Familia-India-",
                "related_urls": [],
                "title": "",
                "mentions": 70,
                "sources": 1,
                "goldstein": -5.0,
                "tone": 2.57662278840068,
                "score": 62.0,
                "keyword": "인도 가족법 개편",
                "hook": "인도의 법 체계가 대대적인 가족법 개편을 앞두고 뜨거운 논란에 휩싸였습니다.",
                "script": "인도의 법적 지형이 바뀝니다. 가족법 개편안이 발표되면서 사회 전반에 걸친 갑론을박이 이어지고 있습니다. 무엇이 어떻게 달라지는지 지금 바로 확인해 보세요.",
                "sentiment": "neutral"
            },
            {
                "record_id": "1310479219",
                "url": "https://www.livemint.com/industry/india-insurgent-brands-growth-report-fmcg-startups-scaling-challenges-11782201284181.html",
                "related_urls": [],
                "title": "",
                "mentions": 50,
                "sources": 1,
                "goldstein": -2.0,
                "tone": 0.23866348448687,
                "score": 37.0
            }
        ],
        "last_updated": "2026-06-25 07:39:03 KST",
        "current_rank": 11
    },
    "Turkey": {
        "gdp_rank": 16,
        "spike_score": 94.0,
        "trends": [
            {
                "record_id": "1310517393",
                "url": "https://www.haberler.com/politika/tbmm-suca-suruklenen-cocuklara-iliskin-arastirma-19983257-haberi/",
                "related_urls": [],
                "title": "",
                "mentions": 60,
                "sources": 1,
                "goldstein": 3.0,
                "tone": -7.57328990228012,
                "score": 47.0,
                "keyword": "범죄 노출 아동",
                "hook": "터키 의회가 범죄의 늪에 빠진 아이들을 구하기 위해 긴급 조사에 착수했습니다.",
                "script": "거리로 내몰린 아이들이 범죄의 사각지대에 방치되어 있습니다. 터키 의회가 범죄에 연루된 아동 실태를 파악하기 위한 조사 보고서를 완성했습니다. 아이들의 미래가 파괴되고 있는 지금, 사회적 보호망은 어디에 있습니까? 즉각적인 대책 없이는 더 큰 비극이 예고됩니다.",
                "sentiment": "negative"
            },
            {
                "record_id": "1310536915",
                "url": "https://www.trthaber.com/haber/gundem/suca-suruklenen-cocuk-taslak-raporu-tamamlandi-949177.html",
                "related_urls": [],
                "title": "",
                "mentions": 60,
                "sources": 1,
                "goldstein": 3.0,
                "tone": -7.69230769230769,
                "score": 47.0
            }
        ],
        "last_updated": "2026-06-25 07:39:03 KST",
        "current_rank": 12
    },
    "Brazil": {
        "gdp_rank": 9,
        "spike_score": 67.0,
        "trends": [
            {
                "record_id": "1310607069",
                "url": "https://acidadeon.com/campinas/lazer-e-cultura/100-anos-do-jockey-club-campineiro-e-comemorado-com-livro-e-exposicao/",
                "related_urls": [],
                "title": "",
                "mentions": 96,
                "sources": 1,
                "goldstein": 3.4,
                "tone": 3.4438775510204,
                "score": 67.0
            }
        ],
        "last_updated": "2026-06-25 07:39:03 KST",
        "current_rank": 13
    },
    "Canada": {
        "gdp_rank": 10,
        "spike_score": 52.0,
        "trends": [
            {
                "record_id": "1310424211",
                "url": "https://www.owensoundsuntimes.com:443/life/fashion-beauty/canadian-made-beauty-brand-wonderblush-holds-its-own-in-an-industry-of-giants",
                "related_urls": [],
                "title": "",
                "mentions": 60,
                "sources": 6,
                "goldstein": -2.0,
                "tone": 5.14452415291539,
                "score": 52.0
            }
        ],
        "last_updated": "2026-06-25 07:39:03 KST",
        "current_rank": 14
    }
}