{
    "United Kingdom": {
        "gdp_rank": 6,
        "spike_score": 2082.5,
        "trends": [
            {
                "record_id": "1308796026",
                "url": "https://www.surreycomet.co.uk/news/national/26191504.million-events-never-plan-says-parkrun-founder-milestone-nears/",
                "related_urls": [
                    "https://www.braintreeandwithamtimes.co.uk/news/national/26191504.million-events-never-plan-says-parkrun-founder-milestone-nears/"
                ],
                "title": "",
                "mentions": 210,
                "sources": 15,
                "goldstein": 2.8,
                "tone": 2.77777777777778,
                "score": 763.5
            },
            {
                "record_id": "1308694251",
                "url": "https://www.stratford-herald.com/national/pm-urged-to-take-courageous-decisions-on-defence-as-he-fights-for-his-future-167875/",
                "related_urls": [
                    "https://www.enfieldindependent.co.uk/news/national/26188430.pm-urged-take-courageous-decisions-defence-fights-future/"
                ],
                "title": "",
                "mentions": 110,
                "sources": 11,
                "goldstein": 2.8,
                "tone": -1.40286185710301,
                "score": 613.0
            },
            {
                "record_id": "1308712483",
                "url": "https://www.edp24.co.uk/news/national/26189227.al-carns-defends-northern-ireland-veterans-following-exit-government/",
                "related_urls": [],
                "title": "",
                "mentions": 100,
                "sources": 10,
                "goldstein": 7.4,
                "tone": -2.60492040520984,
                "score": 368.0
            },
            {
                "record_id": "1308754090",
                "url": "https://www.yourlocalguardian.co.uk/news/national/26191193.elon-musk-becomes-worlds-first-trillionaire-spacex-mega-float/",
                "related_urls": [],
                "title": "",
                "mentions": 56,
                "sources": 8,
                "goldstein": -10.0,
                "tone": -0.156419023334884,
                "score": 188.0
            },
            {
                "record_id": "1308722892",
                "url": "https://www.theargus.co.uk/news/national/26189626.starmer-insists-will-not-walk-away-defence-resignations/",
                "related_urls": [],
                "title": "",
                "mentions": 48,
                "sources": 8,
                "goldstein": 7.0,
                "tone": -2.28613385853979,
                "score": 150.0
            }
        ],
        "last_updated": "2026-06-13 18:32:55 KST",
        "current_rank": 1
    },
    "Australia": {
        "gdp_rank": 13,
        "spike_score": 996.0,
        "trends": [
            {
                "record_id": "1308644904",
                "url": "https://www.yasstribune.com.au/story/9290200/audit-shows-fundraising-is-ridgy-didge-one-nation/",
                "related_urls": [],
                "title": "",
                "mentions": 64,
                "sources": 8,
                "goldstein": 3.0,
                "tone": 0.811604023322045,
                "score": 251.0,
                "keyword": "원네이션 자금 투명성",
                "hook": "호주 정계가 발칵 뒤집혔습니다, 원네이션 당의 수상한 자금 흐름이 감사를 통해 드러났습니다.",
                "script": "감사 결과가 나왔습니다. 원네이션 당의 모금 활동이 정밀 조사 대상이 됐습니다. 투명성 논란이 커지면서 정치권의 비판이 쏟아지고 있습니다. 과연 이 돈의 출처는 어디일까요? 지금 바로 확인하시죠.",
                "sentiment": "neutral"
            },
            {
                "record_id": "1308674473",
                "url": "https://www.dailyadvertiser.com.au/story/9291170/eclectic-life-of-missing-boys-granny-revealed-in-court/",
                "related_urls": [],
                "title": "",
                "mentions": 50,
                "sources": 5,
                "goldstein": 2.8,
                "tone": -3.56495061392947,
                "score": 222.0,
                "keyword": "실종 소년 조모의 비밀",
                "hook": "법정에서 공개된 충격적인 증언, 실종된 소년의 할머니가 숨겨온 이중생활이 드러났습니다.",
                "script": "법정 기록이 공개됐습니다. 실종 사건의 핵심 인물인 할머니의 과거가 베일을 벗었습니다. 평범한 삶 뒤에 감춰진 기이한 행적들이 낱낱이 밝혀지면서 사건은 미궁 속으로 빠져들고 있습니다.",
                "sentiment": "negative"
            },
            {
                "record_id": "1308671966",
                "url": "https://www.inverelltimes.com.au/story/9290774/online-criminals-snaring-the-naive-to-do-the-dirty-work/",
                "related_urls": [],
                "title": "",
                "mentions": 80,
                "sources": 4,
                "goldstein": -10.0,
                "tone": -6.16576904899602,
                "score": 196.0,
                "keyword": "온라인 범죄 조직 주의",
                "hook": "당신의 친절함이 범죄의 도구가 될 수 있습니다, 지금 즉시 온라인 사기를 경계하십시오.",
                "script": "온라인 범죄가 지능화되고 있습니다. 순진한 시민을 유혹해 범죄의 하수인으로 만드는 수법이 기승을 부립니다. 나도 모르는 사이 범죄자가 될 수 있는 위험한 상황, 지금 바로 주의가 필요합니다.",
                "sentiment": "warning"
            },
            {
                "record_id": "1308819097",
                "url": "https://www.examiner.com.au/story/9291512/beachgoers-pull-woman-from-water-after-shark-attack/",
                "related_urls": [],
                "title": "",
                "mentions": 50,
                "sources": 5,
                "goldstein": 7.4,
                "tone": -4.31714866064536,
                "score": 165.5,
                "keyword": "해변 상어 습격",
                "hook": "평화롭던 해변이 순식간에 비명으로 가득 찼습니다, 여성 한 명이 상어의 공격을 받았습니다.",
                "script": "호주 해변에서 끔찍한 사고가 발생했습니다. 수영하던 여성이 상어에게 공격받아 긴급히 구조됐습니다. 현장 목격자들은 아비규환이었던 당시 상황을 전했습니다. 해수욕객들의 각별한 주의가 요구됩니다.",
                "sentiment": "warning"
            },
            {
                "record_id": "1308678710",
                "url": "https://www.theleader.com.au/story/9291368/venue-bins-one-nation-fundraiser-over-safety-concerns/",
                "related_urls": [],
                "title": "",
                "mentions": 120,
                "sources": 6,
                "goldstein": 1.9,
                "tone": -0.980524130801162,
                "score": 161.5,
                "keyword": "원네이션 행사 취소",
                "hook": "안전 우려로 인해 원네이션 당의 행사가 장소 대관 거부라는 초유의 사태를 맞았습니다.",
                "script": "정치적 논란이 안전 문제로 번졌습니다. 원네이션 당이 계획했던 모금 행사가 장소 제공업체로부터 거부당했습니다. 안전을 이유로 내세운 이번 결정, 정치적 탄압일까요 아니면 정당한 안전 조치일까요?",
                "sentiment": "negative"
            }
        ],
        "last_updated": "2026-06-13 18:32:55 KST",
        "current_rank": 2
    },
    "United States": {
        "gdp_rank": 1,
        "spike_score": 800.0,
        "trends": [
            {
                "record_id": "1308737227",
                "url": "https://www.laprovincia.es/sociedad/2026/06/12/obispo-tenerife-leon-xiv-papa-131341245.html",
                "related_urls": [],
                "title": "",
                "mentions": 50,
                "sources": 5,
                "goldstein": 4.0,
                "tone": 4.90922294843863,
                "score": 294.0
            },
            {
                "record_id": "1308647655",
                "url": "https://wlos.com/news/nation-world/repeat-offender-sentenced-to-45-years-after-50day-lego-stealing-spree-police-say-toys-merchandise-stores-organized-retail-theft-watauga-police-department-texas-oklahoma-true-crime",
                "related_urls": [],
                "title": "",
                "mentions": 40,
                "sources": 4,
                "goldstein": -5.0,
                "tone": -6.71936758893281,
                "score": 136.0
            },
            {
                "record_id": "1308799731",
                "url": "https://600wrec.iheart.com/content/2026-06-12-abandoned-boat-leads-massive-search-for-missing-fisherman/",
                "related_urls": [
                    "https://whnz.iheart.com/content/2026-06-12-abandoned-boat-leads-massive-search-for-missing-fisherman/"
                ],
                "title": "",
                "mentions": 80,
                "sources": 1,
                "goldstein": 6.0,
                "tone": -2.53623188405797,
                "score": 134.0
            },
            {
                "record_id": "1308639749",
                "url": "https://kfab.iheart.com/content/2026-06-11-americans-avoid-bank-balances-due-to-anxiety/",
                "related_urls": [],
                "title": "",
                "mentions": 42,
                "sources": 1,
                "goldstein": 7.4,
                "tone": -1.56606968460338,
                "score": 120.0
            },
            {
                "record_id": "1308743949",
                "url": "https://star1043.iheart.com/content/2026-06-12-suspects-at-large-after-armed-robbery-at-kids-lemonade-stand/",
                "related_urls": [],
                "title": "",
                "mentions": 105,
                "sources": 1,
                "goldstein": 5.0,
                "tone": -7.66045548654245,
                "score": 116.0
            }
        ],
        "last_updated": "2026-06-13 18:32:55 KST",
        "current_rank": 3
    },
    "Russia": {
        "gdp_rank": 11,
        "spike_score": 519.5,
        "trends": [
            {
                "record_id": "1308701345",
                "url": "https://www.gazetatema.net/bota/new-york-times-shba-te-duan-te-terheqin-nje-te-treten-e-avioneve-luftarake--i567166",
                "related_urls": [],
                "title": "",
                "mentions": 50,
                "sources": 5,
                "goldstein": 7.0,
                "tone": -0.473237555272692,
                "score": 285.5
            },
            {
                "record_id": "1308831164",
                "url": "http://www.wa.de/politik/tv-doku-enthuellt-wie-ein-wort-putin-zur-russischen-praesidentschaft-verhalf-zr-94349468.html",
                "related_urls": [],
                "title": "",
                "mentions": 50,
                "sources": 4,
                "goldstein": -7.2,
                "tone": -2.89330922242314,
                "score": 145.0
            },
            {
                "record_id": "1308704258",
                "url": "https://www.merkur.de/politik/satellitenbilder-enthuellen-russland-ruestet-an-nato-grenze-auf-zr-94348137.html",
                "related_urls": [],
                "title": "",
                "mentions": 70,
                "sources": 6,
                "goldstein": 0.0,
                "tone": -2.99999999999999,
                "score": 47.0,
                "keyword": "나토 접경 무장",
                "hook": "위성 사진이 포착한 러시아의 나토 국경 지대 군사 증강 움직임이 심상치 않습니다.",
                "script": "위성 이미지에 찍힌 러시아의 군사 기지가 포착되었습니다. 나토와의 국경 지대에 대규모 병력과 장비가 배치되고 있습니다. 긴장감이 최고조에 달한 유럽, 과연 이것은 단순한 훈련일까요, 아니면 실제 충돌의 전조일까요?",
                "sentiment": "warning"
            },
            {
                "record_id": "1308802076",
                "url": "http://www.europesun.com/news/279119839/worlds-tallest-building-lit-up-in-russian-flag-colors",
                "related_urls": [],
                "title": "",
                "mentions": 42,
                "sources": 2,
                "goldstein": 3.4,
                "tone": 4.82456140350877,
                "score": 42.0
            }
        ],
        "last_updated": "2026-06-13 18:32:55 KST",
        "current_rank": 4
    },
    "Germany": {
        "gdp_rank": 3,
        "spike_score": 459.0,
        "trends": [
            {
                "record_id": "1308757848",
                "url": "https://zhurnal.mk/mister-ne-afriken-e-jugut-trashegimtarja-26-vjecare-gjendet-e-vrare-nje-dite-pas-vdekjes-se-bashkepunetorit-te-saj/",
                "related_urls": [],
                "title": "",
                "mentions": 50,
                "sources": 5,
                "goldstein": -10.0,
                "tone": -4.17756847520493,
                "score": 120.0
            },
            {
                "record_id": "1308713409",
                "url": "https://www.antenne.de/nachrichten/bayern/landgericht-google-haftet-fuer-ki-uebersichten",
                "related_urls": [],
                "title": "",
                "mentions": 70,
                "sources": 7,
                "goldstein": -2.0,
                "tone": -3.22466193327256,
                "score": 108.0
            },
            {
                "record_id": "1308743467",
                "url": "https://www.news.de/politik/859710583/trump-bekommt-geburtstagsgeschenk-von-merz-donald-trump-news-der-dpa-aktuell-zu-g7-gipfel-bundesregierung-und-diplomatie/1/",
                "related_urls": [],
                "title": "",
                "mentions": 100,
                "sources": 10,
                "goldstein": 4.0,
                "tone": 5.57656189557405,
                "score": 90.0
            },
            {
                "record_id": "1308833107",
                "url": "https://kosovapress.com/gjermania-zgjat-edhe-nje-vit-pranine-ne-kfor-bundestagu-rinovon-mandatin",
                "related_urls": [],
                "title": "",
                "mentions": 40,
                "sources": 4,
                "goldstein": 3.4,
                "tone": 1.4541612532294,
                "score": 73.0
            },
            {
                "record_id": "1308722230",
                "url": "https://www.kreiszeitung.de/politik/jusos-in-hessen-legen-sich-mit-spd-parteichef-an-klingbeil-kann-es-nicht-zr-94348478.html",
                "related_urls": [],
                "title": "",
                "mentions": 40,
                "sources": 4,
                "goldstein": -2.0,
                "tone": -0.13020833333334,
                "score": 68.0
            }
        ],
        "last_updated": "2026-06-13 18:32:55 KST",
        "current_rank": 5
    },
    "France": {
        "gdp_rank": 7,
        "spike_score": 360.0,
        "trends": [
            {
                "record_id": "1308769341",
                "url": "http://www.autoforum.cz/zajimavosti/v-luxusnim-francouzskem-silnicnim-stihaci-jste-mohli-nahanet-bmw-m5-s-palubnim-telefonem-v-ruce-jedno-z-pouhych-806-vzniklych-aut-je-ted-k-mani/",
                "related_urls": [],
                "title": "",
                "mentions": 190,
                "sources": 1,
                "goldstein": 1.0,
                "tone": 0.936454849498328,
                "score": 204.0
            },
            {
                "record_id": "1308837224",
                "url": "https://udayavani.com/national-news/el-nino-has-arrived-and-will-strengthen-during-monsoon-imd-issues-warning-649213",
                "related_urls": [],
                "title": "",
                "mentions": 50,
                "sources": 1,
                "goldstein": -10.0,
                "tone": -10.517771248787,
                "score": 77.0
            },
            {
                "record_id": "1308738997",
                "url": "https://www.leprogres.fr/politique/2026/06/12/robert-menard-vise-par-une-plainte-pour-diffamation-apres-le-refus-de-marier-un-homme-sous-oqtf",
                "related_urls": [],
                "title": "",
                "mentions": 50,
                "sources": 3,
                "goldstein": -4.0,
                "tone": -11.2314049586777,
                "score": 51.0,
                "keyword": "시장 명예훼손 피소",
                "hook": "프랑스 시장이 불법 체류자의 결혼을 거부했다가 법정 공방에 휘말렸습니다.",
                "script": "로베르 메나르 시장이 벼랑 끝에 섰습니다. 추방 대상자에게 결혼 증명서를 발급하지 않은 혐의로 고소당했기 때문입니다. 인권과 법 집행 사이, 과연 프랑스 사법부는 누구의 손을 들어줄까요? 지금 유럽 전역이 이 재판 결과에 주목하고 있습니다.",
                "sentiment": "negative"
            },
            {
                "record_id": "1308786872",
                "url": "https://www.elcorreogallego.es/sociedad/2026/06/12/visita-papa-leon-xiv-centro-131355819.html",
                "related_urls": [],
                "title": "",
                "mentions": 40,
                "sources": 4,
                "goldstein": 0.0,
                "tone": -0.87209302325581,
                "score": 28.0
            }
        ],
        "last_updated": "2026-06-13 18:32:55 KST",
        "current_rank": 6
    },
    "China": {
        "gdp_rank": 2,
        "spike_score": 347.0,
        "trends": [
            {
                "record_id": "1308660202",
                "url": "https://english.news.cn/20260612/69653f52fb874e2c8c66c0677c871d76/c.html",
                "related_urls": [
                    "https://english.news.cn/20260612/401e9270083944ebab714b8975af2f64/c.html"
                ],
                "title": "",
                "mentions": 109,
                "sources": 1,
                "goldstein": -2.0,
                "tone": 3.35429769392033,
                "score": 144.0
            },
            {
                "record_id": "1308798723",
                "url": "https://www.krvs.org/npr-news/2026-06-12/china-arrests-a-u-s-scholar-with-a-history-of-myanmar-activism-suspected-of-spying",
                "related_urls": [],
                "title": "",
                "mentions": 40,
                "sources": 4,
                "goldstein": -5.0,
                "tone": -4.00801603206413,
                "score": 106.0
            },
            {
                "record_id": "1308694036",
                "url": "http://en.people.cn/n3/2026/0612/c90000-20466998.html",
                "related_urls": [],
                "title": "",
                "mentions": 120,
                "sources": 1,
                "goldstein": 7.0,
                "tone": 3.37078651685393,
                "score": 97.0
            }
        ],
        "last_updated": "2026-06-13 18:32:55 KST",
        "current_rank": 7
    },
    "Canada": {
        "gdp_rank": 10,
        "spike_score": 194.0,
        "trends": [
            {
                "record_id": "1308646852",
                "url": "https://www.bostonherald.com/2026/06/11/canada-officer-killed/",
                "related_urls": [],
                "title": "",
                "mentions": 50,
                "sources": 1,
                "goldstein": -10.0,
                "tone": -6.14406779661016,
                "score": 77.0,
                "keyword": "경찰관 피살 충격",
                "hook": "캐나다에서 현직 경찰관이 순직했다는 비보가 전해지며 전국이 슬픔에 잠겼습니다.",
                "script": "시민을 보호하던 경찰관이 비극적인 죽음을 맞이했습니다. 현재 현장은 봉쇄되었고, 범인을 잡기 위한 대대적인 추격전이 벌어지고 있습니다. 캐나다 전역이 이번 사건을 애도하며 강력한 처벌을 요구하는 목소리가 커지고 있습니다.",
                "sentiment": "negative"
            },
            {
                "record_id": "1308745956",
                "url": "https://www.thewhig.com/news/napanee-eyes-provincial-infrastructure-funding-despite-concerns-over-tight-deadline",
                "related_urls": [],
                "title": "",
                "mentions": 42,
                "sources": 3,
                "goldstein": 7.4,
                "tone": -0.926378168422526,
                "score": 64.0
            },
            {
                "record_id": "1308731104",
                "url": "https://www.niagarafallsreview.ca/news/world/europe/nato-weighs-options-to-defend-europe-as-the-us-plans-for-conflict-elsewhere/article_867c4690-35e2-5394-87c4-a862a61a132a.html",
                "related_urls": [],
                "title": "",
                "mentions": 40,
                "sources": 4,
                "goldstein": -5.0,
                "tone": -1.5279094868449,
                "score": 53.0
            }
        ],
        "last_updated": "2026-06-13 18:32:55 KST",
        "current_rank": 8
    },
    "Brazil": {
        "gdp_rank": 9,
        "spike_score": 174.0,
        "trends": [
            {
                "record_id": "1308812680",
                "url": "https://www.macleayargus.com.au/story/9291511/smiling-boys-faces-transform-a-citys-image-of-evil/",
                "related_urls": [],
                "title": "",
                "mentions": 48,
                "sources": 4,
                "goldstein": -10.0,
                "tone": -1.73556932545953,
                "score": 174.0,
                "keyword": "소년들의 미소",
                "hook": "도시의 악마 같은 이미지를 완전히 바꾼 소년들의 미소가 화제입니다.",
                "script": "공포가 지배하던 도시에 변화의 바람이 불고 있습니다. 범죄의 온상으로 불리던 곳에서 아이들의 환한 미소가 포착되며 사람들의 마음을 움직이고 있습니다. 과연 이 작은 변화가 도시 전체의 잔혹한 역사를 지워낼 수 있을까요?",
                "sentiment": "positive"
            }
        ],
        "last_updated": "2026-06-13 18:32:55 KST",
        "current_rank": 9
    },
    "Italy": {
        "gdp_rank": 8,
        "spike_score": 155.0,
        "trends": [
            {
                "record_id": "1308834385",
                "url": "https://www.zazoom.it/2026-06-13/i-ladri-assaltano-un-negozio-della-piazza-il-colpo-lampo-ripreso-dalle-telecamere/19337791/",
                "related_urls": [],
                "title": "",
                "mentions": 60,
                "sources": 1,
                "goldstein": -9.0,
                "tone": -11.0119047619048,
                "score": 77.0,
                "keyword": "광장 상점 습격",
                "hook": "대낮 광장 한복판에서 벌어진 충격적인 상점 강탈 사건이 CCTV에 포착되었습니다.",
                "script": "평화롭던 이탈리아의 광장이 순식간에 범죄 현장으로 변했습니다. 복면을 쓴 무리가 순식간에 매장에 침입해 물건을 싹쓸이한 뒤 사라졌습니다. 경찰이 수사에 착수했지만, 대담한 범행 수법에 시민들의 불안은 극에 달했습니다.",
                "sentiment": "negative"
            },
            {
                "record_id": "1308824249",
                "url": "https://www.zazoom.it/2026-06-13/la-nautica-italiana-si-conferma-leader-grazie-alla-spinta-dei-superyacht/19337142/",
                "related_urls": [],
                "title": "",
                "mentions": 44,
                "sources": 1,
                "goldstein": 3.4,
                "tone": 5.72139303482587,
                "score": 41.0
            },
            {
                "record_id": "1308834706",
                "url": "https://www.zazoom.it/2026-06-13/garlasco-i-detenuti-di-bollate-ai-giornalisti-stasi-non-e-piu-qui-e-a-casa/19337852/",
                "related_urls": [],
                "title": "",
                "mentions": 50,
                "sources": 1,
                "goldstein": -2.0,
                "tone": -5.13307984790875,
                "score": 37.0
            }
        ],
        "last_updated": "2026-06-13 18:32:55 KST",
        "current_rank": 10
    },
    "Indonesia": {
        "gdp_rank": 15,
        "spike_score": 77.0,
        "trends": [
            {
                "record_id": "1308685120",
                "url": "https://www.aljazeera.net/politics/2026/6/12/%D8%A8%D8%B9%D8%AF-%D8%AA%D8%B1%D8%A7%D8%AC%D8%B9-%D8%A7%D9%84%D8%AF%D8%B9%D9%85-%D8%A7%D9%84%D8%AF%D9%88%D9%84%D9%8A-%D8%AA%D8%AF%D9%87%D9%88%D8%B1-%D9%85%D8%B9%D9%8A%D8%B4%D8%A9",
                "related_urls": [],
                "title": "",
                "mentions": 80,
                "sources": 1,
                "goldstein": 7.0,
                "tone": -4.53047775947283,
                "score": 77.0,
                "keyword": "인도네시아 민생 파탄",
                "hook": "국제 사회의 지원마저 끊겼습니다, 인도네시아의 경제가 벼랑 끝으로 내몰리고 있습니다.",
                "script": "인도네시아 국민들의 삶이 무너지고 있습니다. 국제적인 지원이 급감하면서 물가는 치솟고 생필품은 부족합니다. 경제 위기가 민생을 강타하며 시민들의 분노가 임계점에 도달했습니다. 위기의 현장을 보도합니다.",
                "sentiment": "negative"
            }
        ],
        "last_updated": "2026-06-13 18:32:55 KST",
        "current_rank": 11
    },
    "India": {
        "gdp_rank": 5,
        "spike_score": 57.0,
        "trends": [
            {
                "record_id": "1308807164",
                "url": "https://www.legallyindia.com/convos/topic/484831-Day-Z-and-Short-lisiting-",
                "related_urls": [],
                "title": "",
                "mentions": 60,
                "sources": 1,
                "goldstein": -5.0,
                "tone": 2.38414416392225,
                "score": 57.0
            }
        ],
        "last_updated": "2026-06-13 18:32:55 KST",
        "current_rank": 12
    },
    "Argentina": {
        "gdp_rank": 18,
        "spike_score": 37.0,
        "trends": [
            {
                "record_id": "1308767476",
                "url": "https://www.mdzol.com/policiales/caso-agostina-vega-la-abogada-la-joven-que-2025-denuncio-claudio-barrelier-dio-detalles-la-causa-n1542056",
                "related_urls": [],
                "title": "",
                "mentions": 50,
                "sources": 1,
                "goldstein": -2.0,
                "tone": -3.23159784560144,
                "score": 37.0,
                "keyword": "아고스티나 베가 사건",
                "hook": "법정에서 밝혀진 충격적인 진실, 아고스티나 베가 사건의 담당 변호사가 입을 열었습니다.",
                "script": "클라우디오 바렐리에를 향한 고발, 아고스티나 베가 사건의 전말이 드러나고 있습니다. 변호사가 법정에서 공개한 새로운 증거들이 사건의 판도를 뒤흔들고 있습니다. 아르헨티나 사회를 뒤흔든 이 사건, 결말은 어떻게 될까요?",
                "sentiment": "negative"
            }
        ],
        "last_updated": "2026-06-13 18:32:55 KST",
        "current_rank": 13
    },
    "Mexico": {
        "gdp_rank": 12,
        "spike_score": 36.5,
        "trends": [
            {
                "record_id": "1308743990",
                "url": "https://newsradio1049.iheart.com/content/2026-06-12-anonymous-tip-leads-search-for-guthries-remains-in-mexico/",
                "related_urls": [],
                "title": "",
                "mentions": 50,
                "sources": 1,
                "goldstein": 1.9,
                "tone": -0.858369098712451,
                "score": 36.5,
                "keyword": "실종자 수색 본격화",
                "hook": "익명의 제보 하나가 멕시코 땅에 묻힌 실종자의 진실을 파헤치기 시작했습니다.",
                "script": "수년간 미제로 남았던 실종 사건의 실마리가 잡혔습니다. 익명의 제보자가 가리킨 장소에서 대대적인 수색 작업이 시작되었습니다. 멕시코 당국이 땅을 파헤치며 발견한 것은 무엇일까요? 가족들의 간절한 기다림이 끝날 수 있을지 관심이 집중됩니다.",
                "sentiment": "neutral"
            }
        ],
        "last_updated": "2026-06-13 18:32:55 KST",
        "current_rank": 14
    },
    "Japan": {
        "gdp_rank": 4,
        "spike_score": 33.0,
        "trends": [
            {
                "record_id": "1308670922",
                "url": "https://www.theworldfolio.com/interviews/maple-international-expands-japanese-beauty-brands-worldwide-through-crossborder-growth-and-market-strategy/7431/",
                "related_urls": [],
                "title": "",
                "mentions": 42,
                "sources": 1,
                "goldstein": -2.0,
                "tone": 2.9383429672447,
                "score": 33.0
            }
        ],
        "last_updated": "2026-06-13 18:32:55 KST",
        "current_rank": 15
    }
}